SKLOverlay/__init__.py
SKLOverlay/src/SKLOCDataMods.py
SKLOverlay/src/SKLOCDatasets.py
SKLOverlay/src/SKLOCMainOps.py
SKLOverlay/src/SKLOCMetrics.py
SKLOverlay/src/SKLOCRun.py
SKLOverlay/src/SKLOClassMenu.py
SKLOverlay/src/SKLOStart.py
SKLOverlay/src/__init__.py
SKLOverlay/src/SKLOCCustom/SKLOCCMain.py
SKLOverlay/src/SKLOCCustom/SKLOCC_KN.py
SKLOverlay/src/SKLOCCustom/SKLOCC_MLP.py
SKLOverlay/src/SKLOCCustom/SKLOCC_RF.py
SKLOverlay/src/SKLOCCustom/SKLOCC_SVM.py
SKLOverlay/src/SKLOCCustom/SKLOCC_SVML.py
SKLOverlay/src/SKLOCCustom/__init__.py
SKLOverlay/test/__init__.py
SKLOverlay-1.2.0.dist-info/LICENSE.txt
SKLOverlay-1.2.0.dist-info/METADATA
SKLOverlay-1.2.0.dist-info/WHEEL
SKLOverlay-1.2.0.dist-info/top_level.txt
SKLOverlay-1.2.0.dist-info/RECORD
