Metadata-Version: 2.1
Name: SKLOverlay
Version: 1.2.0
Summary: SKLearn Classification Interface
Home-page: https://github.com/laoluadewoye/SKLOverlay
Author: Laolu Ade
Author-email: laoluadewoye@gmail.com
License: GPLv3
Classifier: License :: OSI Approved :: GNU General Public License v3 (GPLv3)
Classifier: Programming Language :: Python :: 3.11
Classifier: Operating System :: OS Independent
Classifier: Intended Audience :: End Users/Desktop
Classifier: Intended Audience :: Information Technology
Classifier: Natural Language :: English
Classifier: Topic :: Database
Classifier: Topic :: Scientific/Engineering :: Information Analysis
Requires-Python: >=3.11
License-File: LICENSE.txt
Requires-Dist: scikit-learn (>=1.3.0)
Requires-Dist: numpy (>=1.24.3)
Requires-Dist: matplotlib (>=3.7.1)
Requires-Dist: pandas (>=1.5.3)
Requires-Dist: openpyxl (>=3.0.10)
